api_client/__init__.py
api_client/client.py
api_client/exceptions.py
creative_catalyst_client-1.1.9.dist-info/METADATA
creative_catalyst_client-1.1.9.dist-info/WHEEL
creative_catalyst_client-1.1.9.dist-info/top_level.txt
creative_catalyst_client-1.1.9.dist-info/RECORD
