Metadata-Version: 2.4
Name: creative-catalyst-client
Version: 1.1.9
Summary: A client for the Creative Catalyst Engine API.
Author-email: Md Tawhidul Islam <mtawhidulislam7@gmail.com>
Project-URL: Repository, https://github.com/MTawhid7/creative-catalyst-client
Classifier: Programming Language :: Python :: 3
Classifier: License :: OSI Approved :: MIT License
Classifier: Operating System :: OS Independent
Requires-Python: >=3.11
Requires-Dist: requests
Requires-Dist: sseclient-py
